{
	"info": {
		"_postman_id": "f7fae61b-87a4-491f-b22f-3f237d505b02",
		"name": "Final Project end points",
		"schema": "https://schema.getpostman.com/json/collection/v2.1.0/collection.json"
	},
	"item": [
		{
			"name": "get all categories",
			"request": {
				"method": "GET",
				"header": [],
				"url": {
					"raw": "http://localhost:8081/categories",
					"protocol": "http",
					"host": [
						"localhost"
					],
					"port": "8081",
					"path": [
						"categories"
					]
				}
			},
			"response": []
		},
		{
			"name": "create category",
			"request": {
				"method": "POST",
				"header": [],
				"body": {
					"mode": "raw",
					"raw": "{\n    \"type\" : \"road bike\" ,\n    \"description\" : \"Bicycles built for traveling at speed on paved roads\"\n}",
					"options": {
						"raw": {
							"language": "json"
						}
					}
				},
				"url": {
					"raw": "http://localhost:8081/categories",
					"protocol": "http",
					"host": [
						"localhost"
					],
					"port": "8081",
					"path": [
						"categories"
					]
				}
			},
			"response": []
		},
		{
			"name": "create article",
			"request": {
				"method": "POST",
				"header": [],
				"body": {
					"mode": "raw",
					"raw": "{\n    \"name\" : \"Belador 6\" ,\n    \"category\" : \"road bike\" ,\n    \"brand\" : \"Berria\" ,\n    \"description\" : \"collection 2022\" ,\n    \"imageUrl\" : \"../image/berria_belador_6\" ,\n    \"price\" : \"99999.00\",\n    \"size\" : \"L\" ,\n    \"units\" : \"1\" \n}",
					"options": {
						"raw": {
							"language": "json"
						}
					}
				},
				"url": {
					"raw": "http://localhost:8081/articles",
					"protocol": "http",
					"host": [
						"localhost"
					],
					"port": "8081",
					"path": [
						"articles"
					]
				}
			},
			"response": []
		},
		{
			"name": "get All articles",
			"request": {
				"method": "GET",
				"header": [],
				"url": {
					"raw": "http://localhost:8081/articles",
					"protocol": "http",
					"host": [
						"localhost"
					],
					"port": "8081",
					"path": [
						"articles"
					]
				}
			},
			"response": []
		},
		{
			"name": "get articles by category",
			"request": {
				"method": "GET",
				"header": [],
				"url": {
					"raw": "http://localhost:8081/articles?category=road bike",
					"protocol": "http",
					"host": [
						"localhost"
					],
					"port": "8081",
					"path": [
						"articles"
					],
					"query": [
						{
							"key": "category",
							"value": "road bike"
						}
					]
				}
			},
			"response": []
		},
		{
			"name": "create novelty",
			"request": {
				"method": "POST",
				"header": [],
				"body": {
					"mode": "raw",
					"raw": "{\n    \"id\" : \"1\"\n}",
					"options": {
						"raw": {
							"language": "json"
						}
					}
				},
				"url": {
					"raw": "http://localhost:8082/novelties",
					"protocol": "http",
					"host": [
						"localhost"
					],
					"port": "8082",
					"path": [
						"novelties"
					]
				}
			},
			"response": []
		},
		{
			"name": "delete novelty",
			"request": {
				"method": "DELETE",
				"header": [],
				"url": {
					"raw": "http://localhost:8082/novelties/1",
					"protocol": "http",
					"host": [
						"localhost"
					],
					"port": "8082",
					"path": [
						"novelties",
						"1"
					]
				}
			},
			"response": []
		},
		{
			"name": "get All novelties",
			"request": {
				"method": "GET",
				"header": [],
				"url": {
					"raw": "http://localhost:8082/novelties",
					"protocol": "http",
					"host": [
						"localhost"
					],
					"port": "8082",
					"path": [
						"novelties"
					]
				}
			},
			"response": []
		}
	]
}